linear_algebra_ulloa-0.0.2.dist-info/METADATA
linear_algebra_ulloa-0.0.2.dist-info/RECORD
linear_algebra_ulloa-0.0.2.dist-info/WHEEL
linear_algebra_ulloa-0.0.2.dist-info/top_level.txt
linear_lib/__init__.py
linear_lib/linear.py
linear_lib/linear_tests.py
