Metadata-Version: 2.1
Name: linear-algebra-ulloa
Version: 0.0.2
Summary: Vector/Matrix classes - refined rref and fixed a bug. Added author information.
Home-page: https://github.com/ulloaluis/linear-algebra
Author: Luis Ulloa
Author-email: ulloa@stanford.edu
License: UNKNOWN
Platform: UNKNOWN
Classifier: Programming Language :: Python :: 3
Classifier: License :: OSI Approved :: MIT License
Classifier: Operating System :: OS Independent
